dmpdfparserdata.py
dmpdfparserdata-1.0.2.dist-info/DESCRIPTION.rst
dmpdfparserdata-1.0.2.dist-info/METADATA
dmpdfparserdata-1.0.2.dist-info/RECORD
dmpdfparserdata-1.0.2.dist-info/WHEEL
dmpdfparserdata-1.0.2.dist-info/metadata.json
dmpdfparserdata-1.0.2.dist-info/top_level.txt
